shimpy/__init__.py
shimpy/account/__init__.py
shimpy/account/commands.py
shimpy/address/__init__.py
shimpy/address/commands.py
shimpy/cli.py
shimpy/nft/__init__.py
shimpy/nft/commands.py
shimpy/node/__init__.py
shimpy/node/commands.py
shimpy/transactions/__init__.py
shimpy/transactions/commands.py
shimpy-0.0.4.dist-info/LICENSE
shimpy-0.0.4.dist-info/WHEEL
shimpy-0.0.4.dist-info/entry_points.txt
shimpy-0.0.4.dist-info/METADATA
shimpy-0.0.4.dist-info/RECORD
