Metadata-Version: 2.1
Name: shimpy
Version: 0.0.4
Summary: Sample CLI Tool to interact with Shimmer Network.
License: MIT
Author: Kumar Anirudha
Author-email: mail@anirudha.dev
Requires-Python: >=3.11,<4.0
Classifier: License :: OSI Approved :: MIT License
Classifier: Programming Language :: Python :: 3
Classifier: Programming Language :: Python :: 3.11
Requires-Dist: arrow (>=1.2.3,<2.0.0)
Requires-Dist: click (>=8.1.6,<9.0.0)
Requires-Dist: iota-sdk (==1.0.0)
